potyk_lib/__init__.py
potyk_lib/dt/__init__.py
potyk_lib/dt/end.py
potyk_lib/dt/parse.py
potyk_lib/fp/__init__.py
potyk_lib/fp/either.py
potyk_lib/fp/http.py
potyk_lib/fp/if_.py
potyk_lib/fp/match.py
potyk_lib/fp/maybe.py
potyk_lib/fp/pipe.py
potyk_lib/fp/result.py
potyk_lib/iter_/__init__.py
potyk_lib/iter_/dict_.py
potyk_lib/iter_/iter_.py
potyk_lib/iter_/list_.py
potyk_lib/num/__init__.py
potyk_lib/num/decimal.py
potyk_lib/num/try_.py
potyk_lib/phone/__init__.py
potyk_lib/phone/mobile.py
potyk_lib/phone/sanitize.py
potyk_lib-0.6.1.dist-info/WHEEL
potyk_lib-0.6.1.dist-info/METADATA
potyk_lib-0.6.1.dist-info/RECORD
